<MEAS><MEA><ID>783145</ID><TYPE>VOD STREAM</TYPE><INFOS><DESCRIPTION><![CDATA[]]></DESCRIPTION><NB_VUES>860</NB_VUES><NB_LIKES>4</NB_LIKES><NB_COMMENTS>0</NB_COMMENTS><NOTE><AUTORISER>NON</AUTORISER><MOYENNE>0</MOYENNE><NB_VOTES>0</NB_VOTES></NOTE><TITRAGE><TITRE><![CDATA[UN MONDE SANS FIN]]></TITRE><SOUS_TITRE><![CDATA[BA des épisodes 7 et 8]]></SOUS_TITRE></TITRAGE><OPENGRAPH><TYPE>video.other</TYPE></OPENGRAPH></INFOS><CHAINE>0</CHAINE><MEDIA><IMAGES><GRAND>http://media.canal-plus.com/wwwplus/image/5/159/1/VIGNETTE_AUTO_393261_H.jpg</GRAND><PETIT>http://media.canal-plus.com/wwwplus/image/5/159/1/VIGNETTE_AUTO_393260_L.jpg</PETIT></IMAGES></MEDIA><RUBRIQUAGE><UNIVERS>SERIES</UNIVERS><RUBRIQUE>UN MONDE SANS FIN - SAISON 5</RUBRIQUE><CATEGORIE>BA</CATEGORIE></RUBRIQUAGE></MEA><MEA><ID>773313</ID><TYPE>VOD STREAM</TYPE><INFOS><DESCRIPTION><![CDATA[]]></DESCRIPTION><NB_VUES>615</NB_VUES><NB_LIKES>9</NB_LIKES><NB_COMMENTS>0</NB_COMMENTS><NOTE><AUTORISER>NON</AUTORISER><MOYENNE>0</MOYENNE><NB_VOTES>0</NB_VOTES></NOTE><TITRAGE><TITRE><![CDATA[UN MONDE SANS FIN]]></TITRE><SOUS_TITRE><![CDATA[BA des épisodes 5 et 6]]></SOUS_TITRE></TITRAGE><OPENGRAPH><TYPE>video.other</TYPE></OPENGRAPH></INFOS><CHAINE>0</CHAINE><MEDIA><IMAGES><GRAND>http://media.canal-plus.com/wwwplus/image/5/159/1/VIGNETTE_AUTO_387221_H.jpg</GRAND><PETIT>http://media.canal-plus.com/wwwplus/image/5/159/1/VIGNETTE_AUTO_387220_L.jpg</PETIT></IMAGES></MEDIA><RUBRIQUAGE><UNIVERS>SERIES</UNIVERS><RUBRIQUE>UN MONDE SANS FIN - SAISON 5</RUBRIQUE><CATEGORIE>BA</CATEGORIE></RUBRIQUAGE></MEA><MEA><ID>773332</ID><TYPE>VOD STREAM</TYPE><INFOS><DESCRIPTION><![CDATA[]]></DESCRIPTION><NB_VUES>338</NB_VUES><NB_LIKES>0</NB_LIKES><NB_COMMENTS>0</NB_COMMENTS><NOTE><AUTORISER>NON</AUTORISER><MOYENNE>0</MOYENNE><NB_VOTES>0</NB_VOTES></NOTE><TITRAGE><TITRE><![CDATA[UN MONDE SANS FIN]]></TITRE><SOUS_TITRE><![CDATA[BA des épisodes 3 et 4]]></SOUS_TITRE></TITRAGE><OPENGRAPH><TYPE>video.other</TYPE></OPENGRAPH></INFOS><CHAINE>0</CHAINE><MEDIA><IMAGES><GRAND>http://media.canal-plus.com/wwwplus/image/5/159/1/VIGNETTE_AUTO_387257_H.jpg</GRAND><PETIT>http://media.canal-plus.com/wwwplus/image/5/159/1/VIGNETTE_AUTO_387256_L.jpg</PETIT></IMAGES></MEDIA><RUBRIQUAGE><UNIVERS>SERIES</UNIVERS><RUBRIQUE>UN MONDE SANS FIN - SAISON 5</RUBRIQUE><CATEGORIE>BA</CATEGORIE></RUBRIQUAGE></MEA><MEA><ID>770271</ID><TYPE>VOD PROG</TYPE><INFOS><DESCRIPTION><![CDATA[]]></DESCRIPTION><NB_VUES>813</NB_VUES><NB_LIKES>2</NB_LIKES><NB_COMMENTS>0</NB_COMMENTS><NOTE><AUTORISER>NON</AUTORISER><MOYENNE>0</MOYENNE><NB_VOTES>0</NB_VOTES></NOTE><TITRAGE><TITRE><![CDATA[UN MONDE SANS FIN]]></TITRE><SOUS_TITRE><![CDATA[Bande-annonce]]></SOUS_TITRE></TITRAGE><OPENGRAPH><TYPE>video.other</TYPE></OPENGRAPH></INFOS><CHAINE>0</CHAINE><MEDIA><IMAGES><GRAND>http://media.canal-plus.com/wwwplus/image/5/159/1/VIGNETTE_AUTO_385174_H.jpg</GRAND><PETIT>http://media.canal-plus.com/wwwplus/image/5/159/1/VIGNETTE_AUTO_385173_L.jpg</PETIT></IMAGES></MEDIA><RUBRIQUAGE><UNIVERS>SERIES</UNIVERS><RUBRIQUE>UN MONDE SANS FIN - SAISON 5</RUBRIQUE><CATEGORIE>BA</CATEGORIE></RUBRIQUAGE></MEA><MEA><ID>769033</ID><TYPE>VOD PROG</TYPE><INFOS><DESCRIPTION><![CDATA[]]></DESCRIPTION><NB_VUES>278</NB_VUES><NB_LIKES>0</NB_LIKES><NB_COMMENTS>0</NB_COMMENTS><NOTE><AUTORISER>NON</AUTORISER><MOYENNE>0</MOYENNE><NB_VOTES>0</NB_VOTES></NOTE><TITRAGE><TITRE><![CDATA[UN MONDE SANS FIN]]></TITRE><SOUS_TITRE><![CDATA[Teaser 1]]></SOUS_TITRE></TITRAGE><OPENGRAPH><TYPE>video.other</TYPE></OPENGRAPH></INFOS><CHAINE>0</CHAINE><MEDIA><IMAGES><GRAND>http://media.canal-plus.com/wwwplus/image/5/159/1/VIGNETTE_AUTO_384418_H.jpg</GRAND><PETIT>http://media.canal-plus.com/wwwplus/image/5/159/1/VIGNETTE_AUTO_384417_L.jpg</PETIT></IMAGES></MEDIA><RUBRIQUAGE><UNIVERS>SERIES</UNIVERS><RUBRIQUE>UN MONDE SANS FIN - SAISON 5</RUBRIQUE><CATEGORIE>BA</CATEGORIE></RUBRIQUAGE></MEA><MEA><ID>769034</ID><TYPE>VOD PROG</TYPE><INFOS><DESCRIPTION><![CDATA[]]></DESCRIPTION><NB_VUES>159</NB_VUES><NB_LIKES>0</NB_LIKES><NB_COMMENTS>0</NB_COMMENTS><NOTE><AUTORISER>NON</AUTORISER><MOYENNE>0</MOYENNE><NB_VOTES>0</NB_VOTES></NOTE><TITRAGE><TITRE><![CDATA[UN MONDE SANS FIN]]></TITRE><SOUS_TITRE><![CDATA[Teaser 2]]></SOUS_TITRE></TITRAGE><OPENGRAPH><TYPE>video.other</TYPE></OPENGRAPH></INFOS><CHAINE>0</CHAINE><MEDIA><IMAGES><GRAND>http://media.canal-plus.com/wwwplus/image/5/159/1/VIGNETTE_AUTO_384420_H.jpg</GRAND><PETIT>http://media.canal-plus.com/wwwplus/image/5/159/1/VIGNETTE_AUTO_384419_L.jpg</PETIT></IMAGES></MEDIA><RUBRIQUAGE><UNIVERS>SERIES</UNIVERS><RUBRIQUE>UN MONDE SANS FIN - SAISON 5</RUBRIQUE><CATEGORIE>BA</CATEGORIE></RUBRIQUAGE></MEA><MEA><ID>769035</ID><TYPE>VOD PROG</TYPE><INFOS><DESCRIPTION><![CDATA[]]></DESCRIPTION><NB_VUES>83</NB_VUES><NB_LIKES>0</NB_LIKES><NB_COMMENTS>0</NB_COMMENTS><NOTE><AUTORISER>NON</AUTORISER><MOYENNE>0</MOYENNE><NB_VOTES>0</NB_VOTES></NOTE><TITRAGE><TITRE><![CDATA[UN MONDE SANS FIN]]></TITRE><SOUS_TITRE><![CDATA[Teaser 3]]></SOUS_TITRE></TITRAGE><OPENGRAPH><TYPE>video.other</TYPE></OPENGRAPH></INFOS><CHAINE>0</CHAINE><MEDIA><IMAGES><GRAND>http://media.canal-plus.com/wwwplus/image/5/159/1/VIGNETTE_AUTO_384422_H.jpg</GRAND><PETIT>http://media.canal-plus.com/wwwplus/image/5/159/1/VIGNETTE_AUTO_384421_L.jpg</PETIT></IMAGES></MEDIA><RUBRIQUAGE><UNIVERS>SERIES</UNIVERS><RUBRIQUE>UN MONDE SANS FIN - SAISON 5</RUBRIQUE><CATEGORIE>BA</CATEGORIE></RUBRIQUAGE></MEA></MEAS>