<MEAS><MEA><ID>1085797</ID><TYPE>VOD STREAM</TYPE><INFOS><DESCRIPTION><![CDATA[Bande annonce des épisode 17 et 18 de la saison 3 de Scandal]]></DESCRIPTION><NB_VUES>8241</NB_VUES><NB_LIKES>34</NB_LIKES><NB_COMMENTS>9</NB_COMMENTS><NOTE><AUTORISER>NON</AUTORISER><MOYENNE>0</MOYENNE><NB_VOTES>0</NB_VOTES></NOTE><TITRAGE><TITRE><![CDATA[Scandal Saison 3]]></TITRE><SOUS_TITRE><![CDATA[Bande annonce des épisode 17 et 18]]></SOUS_TITRE></TITRAGE><OPENGRAPH><TYPE>video.other</TYPE></OPENGRAPH></INFOS><CHAINE>0</CHAINE><MEDIA><IMAGES><GRAND>http://media.canal-plus.com/wwwplus/image/5/205/3/nip-nip-17606-640x360-suo0v.jpg</GRAND><PETIT>http://media.canal-plus.com/wwwplus/image/5/205/3/nip-nip-17606-145x109-suo0v.jpg</PETIT></IMAGES></MEDIA><RUBRIQUAGE><UNIVERS>SERIES</UNIVERS><RUBRIQUE>SCANDAL_SAISON_3</RUBRIQUE><CATEGORIE>BA</CATEGORIE></RUBRIQUAGE></MEA><MEA><ID>1085088</ID><TYPE>VOD STREAM</TYPE><INFOS><DESCRIPTION><![CDATA[Bande annonce des épisode 15 et 16 de la saison 3 de Scandal]]></DESCRIPTION><NB_VUES>3030</NB_VUES><NB_LIKES>102</NB_LIKES><NB_COMMENTS>6</NB_COMMENTS><NOTE><AUTORISER>NON</AUTORISER><MOYENNE>0</MOYENNE><NB_VOTES>0</NB_VOTES></NOTE><TITRAGE><TITRE><![CDATA[Scandal Saison 3]]></TITRE><SOUS_TITRE><![CDATA[Bande annonce des épisode 15 et 16]]></SOUS_TITRE></TITRAGE><OPENGRAPH><TYPE>video.other</TYPE></OPENGRAPH></INFOS><CHAINE>0</CHAINE><MEDIA><IMAGES><GRAND>http://media.canal-plus.com/wwwplus/image/5/205/3/nip-nip-17456-640x360-m2vkq.jpg</GRAND><PETIT>http://media.canal-plus.com/wwwplus/image/5/205/3/nip-nip-17456-145x109-m2vkq.jpg</PETIT></IMAGES></MEDIA><RUBRIQUAGE><UNIVERS>SERIES</UNIVERS><RUBRIQUE>SCANDAL_SAISON_3</RUBRIQUE><CATEGORIE>BA</CATEGORIE></RUBRIQUAGE></MEA><MEA><ID>1081316</ID><TYPE>VOD STREAM</TYPE><INFOS><DESCRIPTION><![CDATA[Episodes 13 et 14 de la saison 3 de Scandal, diffusion en VM le jeudi à 20h55 sur CANAL+]]></DESCRIPTION><NB_VUES>2496</NB_VUES><NB_LIKES>102</NB_LIKES><NB_COMMENTS>13</NB_COMMENTS><NOTE><AUTORISER>OUI</AUTORISER><MOYENNE>0</MOYENNE><NB_VOTES>0</NB_VOTES></NOTE><TITRAGE><TITRE><![CDATA[Scandal Saison 3]]></TITRE><SOUS_TITRE><![CDATA[Bande annonce des épisode 13 et 14]]></SOUS_TITRE></TITRAGE><OPENGRAPH><TYPE>video.other</TYPE></OPENGRAPH></INFOS><CHAINE>0</CHAINE><MEDIA><IMAGES><GRAND>http://media.canal-plus.com/wwwplus/image/5/205/3/nip-nip-16688-640x360-b2c2z.jpg</GRAND><PETIT>http://media.canal-plus.com/wwwplus/image/5/205/3/nip-nip-16688-145x109-b2c2z.jpg</PETIT></IMAGES></MEDIA><RUBRIQUAGE><UNIVERS>SERIES</UNIVERS><RUBRIQUE>SCANDAL_SAISON_3</RUBRIQUE><CATEGORIE>BA</CATEGORIE></RUBRIQUAGE></MEA><MEA><ID>1077330</ID><TYPE>VOD STREAM</TYPE><INFOS><DESCRIPTION><![CDATA[A Washington, petits et grands secrets refont parfois surface. Le risque ? Détruire des vies, des carrières, et même des idéaux.. heureusement Olivia Pope est là ...]]></DESCRIPTION><NB_VUES>4719</NB_VUES><NB_LIKES>10</NB_LIKES><NB_COMMENTS>1</NB_COMMENTS><NOTE><AUTORISER>OUI</AUTORISER><MOYENNE>0</MOYENNE><NB_VOTES>0</NB_VOTES></NOTE><TITRAGE><TITRE><![CDATA[Scandal Saison 3]]></TITRE><SOUS_TITRE><![CDATA[Bande annonce des épisode 11 et 12]]></SOUS_TITRE></TITRAGE><OPENGRAPH><TYPE>video.other</TYPE></OPENGRAPH></INFOS><CHAINE>0</CHAINE><MEDIA><IMAGES><GRAND>http://media.canal-plus.com/wwwplus/image/5/205/3/nip-nip-15896-640x360-nerpw.jpg</GRAND><PETIT>http://media.canal-plus.com/wwwplus/image/5/205/3/nip-nip-15896-145x109-nerpw.jpg</PETIT></IMAGES></MEDIA><RUBRIQUAGE><UNIVERS>SERIES</UNIVERS><RUBRIQUE>SCANDAL_SAISON_3</RUBRIQUE><CATEGORIE>BA</CATEGORIE></RUBRIQUAGE></MEA><MEA><ID>1070798</ID><TYPE>VOD STREAM</TYPE><INFOS><DESCRIPTION><![CDATA[La maitresse du président s'affiche tous les jeudis.]]></DESCRIPTION><NB_VUES>2730</NB_VUES><NB_LIKES>92</NB_LIKES><NB_COMMENTS>0</NB_COMMENTS><NOTE><AUTORISER>NON</AUTORISER><MOYENNE>0</MOYENNE><NB_VOTES>0</NB_VOTES></NOTE><TITRAGE><TITRE><![CDATA[Scandal Saison 3]]></TITRE><SOUS_TITRE><![CDATA[Des mois que les médias sont au courant]]></SOUS_TITRE></TITRAGE><OPENGRAPH><TYPE>video.other</TYPE></OPENGRAPH></INFOS><CHAINE>0</CHAINE><MEDIA><IMAGES><GRAND>http://media.canal-plus.com/wwwplus/image/5/205/3/nip-nip-14432-640x360-wuhke.jpg</GRAND><PETIT>http://media.canal-plus.com/wwwplus/image/5/205/3/nip-nip-14432-145x109-wuhke.jpg</PETIT></IMAGES></MEDIA><RUBRIQUAGE><UNIVERS>SERIES</UNIVERS><RUBRIQUE>SCANDAL_SAISON_3</RUBRIQUE><CATEGORIE>BA</CATEGORIE></RUBRIQUAGE></MEA><MEA><ID>1070797</ID><TYPE>VOD STREAM</TYPE><INFOS><DESCRIPTION><![CDATA[Le président est infidèle ?! Le président est au coeur de toutes les controverses...]]></DESCRIPTION><NB_VUES>1532</NB_VUES><NB_LIKES>1</NB_LIKES><NB_COMMENTS>0</NB_COMMENTS><NOTE><AUTORISER>NON</AUTORISER><MOYENNE>0</MOYENNE><NB_VOTES>0</NB_VOTES></NOTE><TITRAGE><TITRE><![CDATA[Scandal Saison 3]]></TITRE><SOUS_TITRE><![CDATA[Le président]]></SOUS_TITRE></TITRAGE><OPENGRAPH><TYPE>video.other</TYPE></OPENGRAPH></INFOS><CHAINE>0</CHAINE><MEDIA><IMAGES><GRAND>http://media.canal-plus.com/wwwplus/image/5/205/3/nip-nip-14431-640x360-wepxn.jpg</GRAND><PETIT>http://media.canal-plus.com/wwwplus/image/5/205/3/nip-nip-14431-145x109-wepxn.jpg</PETIT></IMAGES></MEDIA><RUBRIQUAGE><UNIVERS>SERIES</UNIVERS><RUBRIQUE>SCANDAL_SAISON_3</RUBRIQUE><CATEGORIE>BA</CATEGORIE></RUBRIQUAGE></MEA><MEA><ID>1070796</ID><TYPE>VOD STREAM</TYPE><INFOS><DESCRIPTION><![CDATA[La série de tous les succès, Michelle Obama elle-même en est accroc !]]></DESCRIPTION><NB_VUES>2739</NB_VUES><NB_LIKES>160</NB_LIKES><NB_COMMENTS>4</NB_COMMENTS><NOTE><AUTORISER>NON</AUTORISER><MOYENNE>0</MOYENNE><NB_VOTES>0</NB_VOTES></NOTE><TITRAGE><TITRE><![CDATA[Scandal Saison 3]]></TITRE><SOUS_TITRE><![CDATA[La série de tous les succès]]></SOUS_TITRE></TITRAGE><OPENGRAPH><TYPE>video.other</TYPE></OPENGRAPH></INFOS><CHAINE>0</CHAINE><MEDIA><IMAGES><GRAND>http://media.canal-plus.com/wwwplus/image/5/205/3/nip-nip-14430-640x360-a3uye.jpg</GRAND><PETIT>http://media.canal-plus.com/wwwplus/image/5/205/3/nip-nip-14430-145x109-a3uye.jpg</PETIT></IMAGES></MEDIA><RUBRIQUAGE><UNIVERS>SERIES</UNIVERS><RUBRIQUE>SCANDAL_SAISON_3</RUBRIQUE><CATEGORIE>BA</CATEGORIE></RUBRIQUAGE></MEA><MEA><ID>1069002</ID><TYPE>VOD STREAM</TYPE><INFOS><DESCRIPTION><![CDATA[A Washington, petits et grands secrets refont parfois surface. Le risque ? Détruire des vies, des carrières, et même des idéaux.. heureusement Olivia Pope est là ...]]></DESCRIPTION><NB_VUES>2449</NB_VUES><NB_LIKES>2</NB_LIKES><NB_COMMENTS>0</NB_COMMENTS><NOTE><AUTORISER>NON</AUTORISER><MOYENNE>0</MOYENNE><NB_VOTES>0</NB_VOTES></NOTE><TITRAGE><TITRE><![CDATA[Scandal Saison 3]]></TITRE><SOUS_TITRE><![CDATA[Bande annonce des épisode 9 et 10]]></SOUS_TITRE></TITRAGE><OPENGRAPH><TYPE>video.other</TYPE></OPENGRAPH></INFOS><CHAINE>0</CHAINE><MEDIA><IMAGES><GRAND>http://media.canal-plus.com/wwwplus/image/5/205/3/nip-nip-13989-640x360-zgvoz.jpg</GRAND><PETIT>http://media.canal-plus.com/wwwplus/image/5/205/3/nip-nip-13989-145x109-zgvoz.jpg</PETIT></IMAGES></MEDIA><RUBRIQUAGE><UNIVERS>SERIES</UNIVERS><RUBRIQUE>SCANDAL_SAISON_3</RUBRIQUE><CATEGORIE>BA</CATEGORIE></RUBRIQUAGE></MEA><MEA><ID>1066255</ID><TYPE>VOD STREAM</TYPE><INFOS><DESCRIPTION><![CDATA[A Washington, petits et grands secrets refont parfois surface. Le risque ? Détruire des vies, des carrières, et même des idéaux.. heureusement Olivia Pope est là ...]]></DESCRIPTION><NB_VUES>2247</NB_VUES><NB_LIKES>6</NB_LIKES><NB_COMMENTS>1</NB_COMMENTS><NOTE><AUTORISER>NON</AUTORISER><MOYENNE>0</MOYENNE><NB_VOTES>0</NB_VOTES></NOTE><TITRAGE><TITRE><![CDATA[Scandal Saison 3]]></TITRE><SOUS_TITRE><![CDATA[Bande annonce des épisode 7 et 8]]></SOUS_TITRE></TITRAGE><OPENGRAPH><TYPE>video.other</TYPE></OPENGRAPH></INFOS><CHAINE>0</CHAINE><MEDIA><IMAGES><GRAND>http://media.canal-plus.com/wwwplus/image/5/205/3/nip-nip-13470-640x360-vk1ps.jpg</GRAND><PETIT>http://media.canal-plus.com/wwwplus/image/5/205/3/nip-nip-13470-145x109-vk1ps.jpg</PETIT></IMAGES></MEDIA><RUBRIQUAGE><UNIVERS>SERIES</UNIVERS><RUBRIQUE>SCANDAL_SAISON_3</RUBRIQUE><CATEGORIE>BA</CATEGORIE></RUBRIQUAGE></MEA><MEA><ID>1061900</ID><TYPE>VOD STREAM</TYPE><INFOS><DESCRIPTION><![CDATA[Bande-annonce des épisodes 5 et 6]]></DESCRIPTION><NB_VUES>2580</NB_VUES><NB_LIKES>43</NB_LIKES><NB_COMMENTS>2</NB_COMMENTS><NOTE><AUTORISER>NON</AUTORISER><MOYENNE>0</MOYENNE><NB_VOTES>0</NB_VOTES></NOTE><TITRAGE><TITRE><![CDATA[Scandal Saison 3]]></TITRE><SOUS_TITRE><![CDATA[Bande-annonce des épisodes 5 et 6]]></SOUS_TITRE></TITRAGE><OPENGRAPH><TYPE>video.other</TYPE></OPENGRAPH></INFOS><CHAINE>0</CHAINE><MEDIA><IMAGES><GRAND>http://media.canal-plus.com/wwwplus/image/5/205/3/nip-nip-12606-640x360-q29rv.jpg</GRAND><PETIT>http://media.canal-plus.com/wwwplus/image/5/205/3/nip-nip-12606-145x109-q29rv.jpg</PETIT></IMAGES></MEDIA><RUBRIQUAGE><UNIVERS>SERIES</UNIVERS><RUBRIQUE>SCANDAL_SAISON_3</RUBRIQUE><CATEGORIE>BA</CATEGORIE></RUBRIQUAGE></MEA><MEA><ID>1058774</ID><TYPE>VOD STREAM</TYPE><INFOS><DESCRIPTION><![CDATA[Dernier épisode de la saison 3 pleine de rebondissements de Scandal]]></DESCRIPTION><NB_VUES>2844</NB_VUES><NB_LIKES>17</NB_LIKES><NB_COMMENTS>5</NB_COMMENTS><NOTE><AUTORISER>OUI</AUTORISER><MOYENNE>0</MOYENNE><NB_VOTES>0</NB_VOTES></NOTE><TITRAGE><TITRE><![CDATA[Scandal Saison 3]]></TITRE><SOUS_TITRE><![CDATA[Extrait de l'épisode 18]]></SOUS_TITRE></TITRAGE><OPENGRAPH><TYPE>video.other</TYPE></OPENGRAPH></INFOS><CHAINE>0</CHAINE><MEDIA><IMAGES><GRAND>http://media.canal-plus.com/wwwplus/image/5/205/2/nip-nip-11946-640x360-nhrmn.jpg</GRAND><PETIT>http://media.canal-plus.com/wwwplus/image/5/205/2/nip-nip-11946-145x109-nhrmn.jpg</PETIT></IMAGES></MEDIA><RUBRIQUAGE><UNIVERS>SERIES</UNIVERS><RUBRIQUE>SCANDAL_SAISON_3</RUBRIQUE><CATEGORIE>EXTRAITS</CATEGORIE></RUBRIQUAGE></MEA><MEA><ID>1058151</ID><TYPE>VOD STREAM</TYPE><INFOS><DESCRIPTION><![CDATA[Avant de voir la saison 3, le résumé en vidéo des saisons 1 et 2 de la série Scandal]]></DESCRIPTION><NB_VUES>4872</NB_VUES><NB_LIKES>208</NB_LIKES><NB_COMMENTS>29</NB_COMMENTS><NOTE><AUTORISER>OUI</AUTORISER><MOYENNE>0</MOYENNE><NB_VOTES>0</NB_VOTES></NOTE><TITRAGE><TITRE><![CDATA[Scandal]]></TITRE><SOUS_TITRE><![CDATA[Résumé des saisons 1 et 2]]></SOUS_TITRE></TITRAGE><OPENGRAPH><TYPE>video.other</TYPE></OPENGRAPH></INFOS><CHAINE>0</CHAINE><MEDIA><IMAGES><GRAND>http://media.canal-plus.com/wwwplus/image/5/205/1/nip-nip-11798-640x360-zvnzm.jpg</GRAND><PETIT>http://media.canal-plus.com/wwwplus/image/5/205/1/nip-nip-11798-145x109-zvnzm.jpg</PETIT></IMAGES></MEDIA><RUBRIQUAGE><UNIVERS>SERIES</UNIVERS><RUBRIQUE>SCANDAL_SAISON_3</RUBRIQUE><CATEGORIE>RESUMES</CATEGORIE></RUBRIQUAGE></MEA><MEA><ID>1057956</ID><TYPE>VOD STREAM</TYPE><INFOS><DESCRIPTION><![CDATA[A Washington, petits et grands secrets refont parfois surface. Le risque ? Détruire des vies, des carrières, et même des idéaux.. heuresement Olivia Pope est là ...]]></DESCRIPTION><NB_VUES>1010</NB_VUES><NB_LIKES>406</NB_LIKES><NB_COMMENTS>14</NB_COMMENTS><NOTE><AUTORISER>OUI</AUTORISER><MOYENNE>0</MOYENNE><NB_VOTES>0</NB_VOTES></NOTE><TITRAGE><TITRE><![CDATA[Scandal Saison 3]]></TITRE><SOUS_TITRE><![CDATA[Bande annonce des épisode 3 et 4]]></SOUS_TITRE></TITRAGE><OPENGRAPH><TYPE>video.other</TYPE></OPENGRAPH></INFOS><CHAINE>0</CHAINE><MEDIA><IMAGES><GRAND>http://media.canal-plus.com/wwwplus/image/5/205/3/nip-nip-11736-640x360-uwrxw.jpg</GRAND><PETIT>http://media.canal-plus.com/wwwplus/image/5/205/3/nip-nip-11736-145x109-uwrxw.jpg</PETIT></IMAGES></MEDIA><RUBRIQUAGE><UNIVERS>SERIES</UNIVERS><RUBRIQUE>SCANDAL_SAISON_3</RUBRIQUE><CATEGORIE>BA</CATEGORIE></RUBRIQUAGE></MEA><MEA><ID>1050381</ID><TYPE>VOD STREAM</TYPE><INFOS><DESCRIPTION><![CDATA[Abby est envoyée à la maison blanche pour remplacer Olivia. Ce n'est pas du goût de tout le monde...]]></DESCRIPTION><NB_VUES>8270</NB_VUES><NB_LIKES>54</NB_LIKES><NB_COMMENTS>8</NB_COMMENTS><NOTE><AUTORISER>OUI</AUTORISER><MOYENNE>0</MOYENNE><NB_VOTES>0</NB_VOTES></NOTE><TITRAGE><TITRE><![CDATA[Scandal Saison 3]]></TITRE><SOUS_TITRE><![CDATA[Extrait de l'épisode 16]]></SOUS_TITRE></TITRAGE><OPENGRAPH><TYPE>video.other</TYPE></OPENGRAPH></INFOS><CHAINE>0</CHAINE><MEDIA><IMAGES><GRAND>http://media.canal-plus.com/wwwplus/image/5/205/2/nip-nip-9997-640x360-_H.jpg</GRAND><PETIT>http://media.canal-plus.com/wwwplus/image/5/205/2/nip-nip-9997-145x109-_L.jpg</PETIT></IMAGES></MEDIA><RUBRIQUAGE><UNIVERS>SERIES</UNIVERS><RUBRIQUE>SCANDAL_SAISON_3</RUBRIQUE><CATEGORIE>EXTRAITS</CATEGORIE></RUBRIQUAGE></MEA><MEA><ID>1046153</ID><TYPE>VOD STREAM</TYPE><INFOS><DESCRIPTION><![CDATA[A 1h de leur interview télévisée, Fitz et sa famille ne sont toujours pas disponibles. Olivia va devoir prendre les choses en main...]]></DESCRIPTION><NB_VUES>9439</NB_VUES><NB_LIKES>120</NB_LIKES><NB_COMMENTS>18</NB_COMMENTS><NOTE><AUTORISER>NON</AUTORISER><MOYENNE>0</MOYENNE><NB_VOTES>0</NB_VOTES></NOTE><TITRAGE><TITRE><![CDATA[Scandal Saison 3]]></TITRE><SOUS_TITRE><![CDATA[Extrait de l'épisode 15]]></SOUS_TITRE></TITRAGE><OPENGRAPH><TYPE>video.other</TYPE></OPENGRAPH></INFOS><CHAINE>0</CHAINE><MEDIA><IMAGES><GRAND>http://media.canal-plus.com/wwwplus/image/5/205/2/nip-nip-8888-640x360-_H.jpg</GRAND><PETIT>http://media.canal-plus.com/wwwplus/image/5/205/2/nip-nip-8888-145x109-_L.jpg</PETIT></IMAGES></MEDIA><RUBRIQUAGE><UNIVERS>SERIES</UNIVERS><RUBRIQUE>SCANDAL_SAISON_3</RUBRIQUE><CATEGORIE>EXTRAITS</CATEGORIE></RUBRIQUAGE></MEA><MEA><ID>1042962</ID><TYPE>VOD STREAM</TYPE><INFOS><DESCRIPTION><![CDATA[Olivia demande à son père d'avoir pour une fois une conversation normale...]]></DESCRIPTION><NB_VUES>7693</NB_VUES><NB_LIKES>90</NB_LIKES><NB_COMMENTS>22</NB_COMMENTS><NOTE><AUTORISER>NON</AUTORISER><MOYENNE>0</MOYENNE><NB_VOTES>0</NB_VOTES></NOTE><TITRAGE><TITRE><![CDATA[Scandal Saison 3]]></TITRE><SOUS_TITRE><![CDATA[Extrait de l'épisode 14]]></SOUS_TITRE></TITRAGE><OPENGRAPH><TYPE>video.other</TYPE></OPENGRAPH></INFOS><CHAINE>0</CHAINE><MEDIA><IMAGES><GRAND>http://media.canal-plus.com/wwwplus/image/5/205/2/nip-nip-8168-640x360-_H.jpg</GRAND><PETIT>http://media.canal-plus.com/wwwplus/image/5/205/2/nip-nip-8168-145x109-_L.jpg</PETIT></IMAGES></MEDIA><RUBRIQUAGE><UNIVERS>SERIES</UNIVERS><RUBRIQUE>SCANDAL_SAISON_3</RUBRIQUE><CATEGORIE>EXTRAITS</CATEGORIE></RUBRIQUAGE></MEA><MEA><ID>1042225</ID><TYPE>VOD STREAM</TYPE><INFOS><DESCRIPTION><![CDATA[A Washington, petits et grands secrets refont parfois surface. Le risque ? Détruire des vies, des carrières, et même des idéaux.. heureusement Olivia Pope est là ...]]></DESCRIPTION><NB_VUES>2013</NB_VUES><NB_LIKES>37</NB_LIKES><NB_COMMENTS>8</NB_COMMENTS><NOTE><AUTORISER>OUI</AUTORISER><MOYENNE>0</MOYENNE><NB_VOTES>0</NB_VOTES></NOTE><TITRAGE><TITRE><![CDATA[Scandal Saison 3]]></TITRE><SOUS_TITRE><![CDATA[A partir du 24 Avril sur CANAL+]]></SOUS_TITRE></TITRAGE><OPENGRAPH><TYPE>video.other</TYPE></OPENGRAPH></INFOS><CHAINE>0</CHAINE><MEDIA><IMAGES><GRAND>http://media.canal-plus.com/wwwplus/image/5/205/3/nip-nip-8012-640x360-_H.jpg</GRAND><PETIT>http://media.canal-plus.com/wwwplus/image/5/205/3/nip-nip-8012-145x109-_L.jpg</PETIT></IMAGES></MEDIA><RUBRIQUAGE><UNIVERS>SERIES</UNIVERS><RUBRIQUE>SCANDAL_SAISON_3</RUBRIQUE><CATEGORIE>BA</CATEGORIE></RUBRIQUAGE></MEA><MEA><ID>1038777</ID><TYPE>VOD STREAM</TYPE><INFOS><DESCRIPTION><![CDATA[Jake récite un étrange monologue...]]></DESCRIPTION><NB_VUES>1585</NB_VUES><NB_LIKES>62</NB_LIKES><NB_COMMENTS>8</NB_COMMENTS><NOTE><AUTORISER>NON</AUTORISER><MOYENNE>0</MOYENNE><NB_VOTES>0</NB_VOTES></NOTE><TITRAGE><TITRE><![CDATA[Scandal Saison 3]]></TITRE><SOUS_TITRE><![CDATA[Extrait de l'épisode 13]]></SOUS_TITRE></TITRAGE><OPENGRAPH><TYPE>video.other</TYPE></OPENGRAPH></INFOS><CHAINE>0</CHAINE><MEDIA><IMAGES><GRAND>http://media.canal-plus.com/wwwplus/image/5/205/2/nip-nip-7227-640x360-_H.jpg</GRAND><PETIT>http://media.canal-plus.com/wwwplus/image/5/205/2/nip-nip-7227-145x109-_L.jpg</PETIT></IMAGES></MEDIA><RUBRIQUAGE><UNIVERS>SERIES</UNIVERS><RUBRIQUE>SCANDAL_SAISON_3</RUBRIQUE><CATEGORIE>EXTRAITS</CATEGORIE></RUBRIQUAGE></MEA><MEA><ID>1038778</ID><TYPE>VOD STREAM</TYPE><INFOS><DESCRIPTION><![CDATA[Entre Olivia et Jake les choses sont toujours aussi compliquées... Ils discutent de ça autour d'une bouteille de vin]]></DESCRIPTION><NB_VUES>4493</NB_VUES><NB_LIKES>80</NB_LIKES><NB_COMMENTS>6</NB_COMMENTS><NOTE><AUTORISER>NON</AUTORISER><MOYENNE>0</MOYENNE><NB_VOTES>0</NB_VOTES></NOTE><TITRAGE><TITRE><![CDATA[Scandal Saison 3]]></TITRE><SOUS_TITRE><![CDATA[Extrait de l'épisode 13 - Jake et Olivia...]]></SOUS_TITRE></TITRAGE><OPENGRAPH><TYPE>video.other</TYPE></OPENGRAPH></INFOS><CHAINE>0</CHAINE><MEDIA><IMAGES><GRAND>http://media.canal-plus.com/wwwplus/image/5/205/2/nip-nip-7228-640x360-_H.jpg</GRAND><PETIT>http://media.canal-plus.com/wwwplus/image/5/205/2/nip-nip-7228-145x109-_L.jpg</PETIT></IMAGES></MEDIA><RUBRIQUAGE><UNIVERS>SERIES</UNIVERS><RUBRIQUE>SCANDAL_SAISON_3</RUBRIQUE><CATEGORIE>EXTRAITS</CATEGORIE></RUBRIQUAGE></MEA><MEA><ID>1034896</ID><TYPE>VOD STREAM</TYPE><INFOS><DESCRIPTION><![CDATA[Olivia et le président sont encore une fois en train de se disputer violemment...]]></DESCRIPTION><NB_VUES>6005</NB_VUES><NB_LIKES>126</NB_LIKES><NB_COMMENTS>16</NB_COMMENTS><NOTE><AUTORISER>OUI</AUTORISER><MOYENNE>0</MOYENNE><NB_VOTES>0</NB_VOTES></NOTE><TITRAGE><TITRE><![CDATA[Scandal Saison 3]]></TITRE><SOUS_TITRE><![CDATA[Extrait de l'épisode 12]]></SOUS_TITRE></TITRAGE><OPENGRAPH><TYPE>video.other</TYPE></OPENGRAPH></INFOS><CHAINE>0</CHAINE><MEDIA><IMAGES><GRAND>http://media.canal-plus.com/wwwplus/image/5/205/2/nip-nip-6350-640x360-_H.jpg</GRAND><PETIT>http://media.canal-plus.com/wwwplus/image/5/205/2/nip-nip-6350-145x109-_L.jpg</PETIT></IMAGES></MEDIA><RUBRIQUAGE><UNIVERS>SERIES</UNIVERS><RUBRIQUE>SCANDAL_SAISON_3</RUBRIQUE><CATEGORIE>EXTRAITS</CATEGORIE></RUBRIQUAGE></MEA><MEA><ID>1030765</ID><TYPE>VOD STREAM</TYPE><INFOS><DESCRIPTION><![CDATA[Si Olivia consacre sa vie à protéger l'image et les secrets des élites de la Nation, elle a pris tous les risques en entretenant une liaison avec le Président. Les membres de son équipe ont eux aussi de lourds secrets à cacher. Des têtes pourraient tomber et des carrières s'effondrer. Les retrouvailles d'Olivia avec son père, le chef du B613, ont également un impact particulièrement important sur sa vie...]]></DESCRIPTION><NB_VUES>5892</NB_VUES><NB_LIKES>1</NB_LIKES><NB_COMMENTS>0</NB_COMMENTS><NOTE><AUTORISER>OUI</AUTORISER><MOYENNE>0</MOYENNE><NB_VOTES>0</NB_VOTES></NOTE><TITRAGE><TITRE><![CDATA[Scandal Saison 3]]></TITRE><SOUS_TITRE><![CDATA[Extrait de l'épisode 11]]></SOUS_TITRE></TITRAGE><OPENGRAPH><TYPE>video.other</TYPE></OPENGRAPH></INFOS><CHAINE>0</CHAINE><MEDIA><IMAGES><GRAND>http://media.canal-plus.com/wwwplus/image/5/205/2/nip-nip-5383-640x360-_H.jpg</GRAND><PETIT>http://media.canal-plus.com/wwwplus/image/5/205/2/nip-nip-5383-145x109-_L.jpg</PETIT></IMAGES></MEDIA><RUBRIQUAGE><UNIVERS>SERIES</UNIVERS><RUBRIQUE>SCANDAL_SAISON_3</RUBRIQUE><CATEGORIE>EXTRAITS</CATEGORIE></RUBRIQUAGE></MEA><MEA><ID>1030764</ID><TYPE>VOD STREAM</TYPE><INFOS><DESCRIPTION><![CDATA[Les retrouvailles d'Olivia Pope et de son père, le chef du B613, ont un impact particulièrement important sur la vie de l'experte en gestion de crises. Tandis que Fitz tente encore de démeler les ficelles de l'histoire de Rowan, et Maya Pope, Olivia prend tout le monde de vitesse, et comprend ce qui a poussé son père à agir ainsi. Olivia ayant organisé la fuite et l'exil de sa mère, pour la protéger de Rowan, elle découvre finalement le vrai visage de celle-ci. Trop tard ? Quinn tente pour sa part un retour au sein du clan Pope]]></DESCRIPTION><NB_VUES>2860</NB_VUES><NB_LIKES>1</NB_LIKES><NB_COMMENTS>0</NB_COMMENTS><NOTE><AUTORISER>OUI</AUTORISER><MOYENNE>0</MOYENNE><NB_VOTES>0</NB_VOTES></NOTE><TITRAGE><TITRE><![CDATA[Scandal Saison 3]]></TITRE><SOUS_TITRE><![CDATA[Résumé de l'épisode 10]]></SOUS_TITRE></TITRAGE><OPENGRAPH><TYPE>video.other</TYPE></OPENGRAPH></INFOS><CHAINE>0</CHAINE><MEDIA><IMAGES><GRAND>http://media.canal-plus.com/wwwplus/image/5/205/1/nip-nip-5382-640x360-_H.jpg</GRAND><PETIT>http://media.canal-plus.com/wwwplus/image/5/205/1/nip-nip-5382-145x109-_L.jpg</PETIT></IMAGES></MEDIA><RUBRIQUAGE><UNIVERS>SERIES</UNIVERS><RUBRIQUE>SCANDAL_SAISON_3</RUBRIQUE><CATEGORIE>RESUMES</CATEGORIE></RUBRIQUAGE></MEA><MEA><ID>989752</ID><TYPE>VOD STREAM</TYPE><INFOS><DESCRIPTION><![CDATA[Fitz a provoqué le face à face avec Rowan. Mais une fois encore, c'est Olivia qui comprend avant les autres les secrets, et les non dits... Son père à raison, elle représente LA porte de sortie par excellence.]]></DESCRIPTION><NB_VUES>9575</NB_VUES><NB_LIKES>39</NB_LIKES><NB_COMMENTS>30</NB_COMMENTS><NOTE><AUTORISER>NON</AUTORISER><MOYENNE>0</MOYENNE><NB_VOTES>0</NB_VOTES></NOTE><TITRAGE><TITRE><![CDATA[SCANDAL]]></TITRE><SOUS_TITRE><![CDATA[Saison 3 -  Extrait de l'épisode 10]]></SOUS_TITRE></TITRAGE><OPENGRAPH><TYPE>video.other</TYPE></OPENGRAPH></INFOS><CHAINE>0</CHAINE><MEDIA><IMAGES><GRAND>http://media.canal-plus.com/wwwplus/image/5/205/2/SCANDAL_SAISON_3_EXTRAITS_131217_CAN_391663_image_H.jpg</GRAND><PETIT>http://media.canal-plus.com/wwwplus/image/5/205/2/SCANDAL_SAISON_3_EXTRAITS_131217_CAN_391663_image_L.jpg</PETIT></IMAGES></MEDIA><RUBRIQUAGE><UNIVERS>SERIES</UNIVERS><RUBRIQUE>SCANDAL_SAISON_3</RUBRIQUE><CATEGORIE>EXTRAITS</CATEGORIE></RUBRIQUAGE></MEA><MEA><ID>985992</ID><TYPE>VOD STREAM</TYPE><INFOS><DESCRIPTION><![CDATA[Qui de Huck ou de Quinn va finalement prendre son pied en torturant l'autre ?]]></DESCRIPTION><NB_VUES>6967</NB_VUES><NB_LIKES>180</NB_LIKES><NB_COMMENTS>47</NB_COMMENTS><NOTE><AUTORISER>NON</AUTORISER><MOYENNE>0</MOYENNE><NB_VOTES>0</NB_VOTES></NOTE><TITRAGE><TITRE><![CDATA[SCANDAL]]></TITRE><SOUS_TITRE><![CDATA[Saison 3 -  Extrait de l'épisode 9 -Yolo]]></SOUS_TITRE></TITRAGE><OPENGRAPH><TYPE>video.other</TYPE></OPENGRAPH></INFOS><CHAINE>0</CHAINE><MEDIA><IMAGES><GRAND>http://media.canal-plus.com/wwwplus/image/5/205/2/SCANDAL_SAISON_3_EXTRAITS_131210_CAN_389644_image_H.jpg</GRAND><PETIT>http://media.canal-plus.com/wwwplus/image/5/205/2/SCANDAL_SAISON_3_EXTRAITS_131210_CAN_389644_image_L.jpg</PETIT></IMAGES></MEDIA><RUBRIQUAGE><UNIVERS>SERIES</UNIVERS><RUBRIQUE>SCANDAL_SAISON_3</RUBRIQUE><CATEGORIE>EXTRAITS</CATEGORIE></RUBRIQUAGE></MEA><MEA><ID>978668</ID><TYPE>VOD STREAM</TYPE><INFOS><DESCRIPTION><![CDATA[Le plan B de Fitz pour vivre la vie de ses rèves avec Olivia ...]]></DESCRIPTION><NB_VUES>8880</NB_VUES><NB_LIKES>157</NB_LIKES><NB_COMMENTS>26</NB_COMMENTS><NOTE><AUTORISER>NON</AUTORISER><MOYENNE>0</MOYENNE><NB_VOTES>0</NB_VOTES></NOTE><TITRAGE><TITRE><![CDATA[SCANDAL]]></TITRE><SOUS_TITRE><![CDATA[Saison 3 -  Extrait de l'épisode 8 -Vermont is for lovers too]]></SOUS_TITRE></TITRAGE><OPENGRAPH><TYPE>video.other</TYPE></OPENGRAPH></INFOS><CHAINE>0</CHAINE><MEDIA><IMAGES><GRAND>http://media.canal-plus.com/wwwplus/image/5/205/2/VIGNETTE_AUTO_497874_H.jpg</GRAND><PETIT>http://media.canal-plus.com/wwwplus/image/5/205/2/VIGNETTE_AUTO_497873_L.jpg</PETIT></IMAGES></MEDIA><RUBRIQUAGE><UNIVERS>SERIES</UNIVERS><RUBRIQUE>SCANDAL_SAISON_3</RUBRIQUE><CATEGORIE>EXTRAITS</CATEGORIE></RUBRIQUAGE></MEA><MEA><ID>978667</ID><TYPE>VOD STREAM</TYPE><INFOS><DESCRIPTION><![CDATA[Mellie et Fitz dans leurs jeunes années : un amour de jeunesse, ou la construction méticuleuse d'une ascension?]]></DESCRIPTION><NB_VUES>5232</NB_VUES><NB_LIKES>2</NB_LIKES><NB_COMMENTS>0</NB_COMMENTS><NOTE><AUTORISER>NON</AUTORISER><MOYENNE>0</MOYENNE><NB_VOTES>0</NB_VOTES></NOTE><TITRAGE><TITRE><![CDATA[SCANDAL]]></TITRE><SOUS_TITRE><![CDATA[Saison 3 -  Extrait de l'épisode 7 -Everything's coming up Mellie]]></SOUS_TITRE></TITRAGE><OPENGRAPH><TYPE>video.other</TYPE></OPENGRAPH></INFOS><CHAINE>0</CHAINE><MEDIA><IMAGES><GRAND>http://media.canal-plus.com/wwwplus/image/5/205/2/SCANDAL_SAISON_3_EXTRAITS_131126_CAN_385629_image_H.jpg</GRAND><PETIT>http://media.canal-plus.com/wwwplus/image/5/205/2/SCANDAL_SAISON_3_EXTRAITS_131126_CAN_385629_image_L.jpg</PETIT></IMAGES></MEDIA><RUBRIQUAGE><UNIVERS>SERIES</UNIVERS><RUBRIQUE>SCANDAL_SAISON_3</RUBRIQUE><CATEGORIE>EXTRAITS</CATEGORIE></RUBRIQUAGE></MEA><MEA><ID>971100</ID><TYPE>VOD STREAM</TYPE><INFOS><DESCRIPTION><![CDATA[Olivia vs. Fitz : la révélation de Liv sur ce qu'il y avait réellement de l'avion Global airline de l'opération Remington ...]]></DESCRIPTION><NB_VUES>7310</NB_VUES><NB_LIKES>0</NB_LIKES><NB_COMMENTS>0</NB_COMMENTS><NOTE><AUTORISER>NON</AUTORISER><MOYENNE>0</MOYENNE><NB_VOTES>0</NB_VOTES></NOTE><TITRAGE><TITRE><![CDATA[SCANDAL]]></TITRE><SOUS_TITRE><![CDATA[Saison 3 -  Extrait de l'épisode 6 - Icarus]]></SOUS_TITRE></TITRAGE><OPENGRAPH><TYPE>video.other</TYPE></OPENGRAPH></INFOS><CHAINE>0</CHAINE><MEDIA><IMAGES><GRAND>http://media.canal-plus.com/wwwplus/image/5/205/2/VIGNETTE_AUTO_494706_H.jpg</GRAND><PETIT>http://media.canal-plus.com/wwwplus/image/5/205/2/VIGNETTE_AUTO_494705_L.jpg</PETIT></IMAGES></MEDIA><RUBRIQUAGE><UNIVERS>SERIES</UNIVERS><RUBRIQUE>SCANDAL_SAISON_3</RUBRIQUE><CATEGORIE>EXTRAITS</CATEGORIE></RUBRIQUAGE></MEA><MEA><ID>967519</ID><TYPE>VOD STREAM</TYPE><INFOS><DESCRIPTION><![CDATA[A Washington, petits et grands secrets refont parfois surface. Le risque ? Détruire des vies, des carrières, et même des idéaux.. heuresement Olivia Pope est là ...]]></DESCRIPTION><NB_VUES>1605</NB_VUES><NB_LIKES>0</NB_LIKES><NB_COMMENTS>0</NB_COMMENTS><NOTE><AUTORISER>OUI</AUTORISER><MOYENNE>0</MOYENNE><NB_VOTES>0</NB_VOTES></NOTE><TITRAGE><TITRE><![CDATA[SCANDAL]]></TITRE><SOUS_TITRE><![CDATA[Saison 3 -  Résumé de l'épisode 4]]></SOUS_TITRE></TITRAGE><OPENGRAPH><TYPE>video.other</TYPE></OPENGRAPH></INFOS><CHAINE>0</CHAINE><MEDIA><IMAGES><GRAND>http://media.canal-plus.com/wwwplus/image/5/205/1/SCANDAL_SAISON_3_RESUMES_131107_CAN_380025_image_H.jpg</GRAND><PETIT>http://media.canal-plus.com/wwwplus/image/5/205/1/SCANDAL_SAISON_3_RESUMES_131107_CAN_380025_image_L.jpg</PETIT></IMAGES></MEDIA><RUBRIQUAGE><UNIVERS>SERIES</UNIVERS><RUBRIQUE>SCANDAL_SAISON_3</RUBRIQUE><CATEGORIE>RESUMES</CATEGORIE></RUBRIQUAGE></MEA><MEA><ID>967518</ID><TYPE>VOD STREAM</TYPE><INFOS><DESCRIPTION><![CDATA[Petite leçon de communication politique : Fitz ne vaut plus rien sur le marché ...]]></DESCRIPTION><NB_VUES>5284</NB_VUES><NB_LIKES>6</NB_LIKES><NB_COMMENTS>0</NB_COMMENTS><NOTE><AUTORISER>NON</AUTORISER><MOYENNE>0</MOYENNE><NB_VOTES>0</NB_VOTES></NOTE><TITRAGE><TITRE><![CDATA[SCANDAL]]></TITRE><SOUS_TITRE><![CDATA[Saison 3 -  Extrait de l'épisode 5 - More cattle, less bull]]></SOUS_TITRE></TITRAGE><OPENGRAPH><TYPE>video.other</TYPE></OPENGRAPH></INFOS><CHAINE>0</CHAINE><MEDIA><IMAGES><GRAND>http://media.canal-plus.com/wwwplus/image/5/205/2/SCANDAL_SAISON_3_EXTRAITS_131107_CAN_380024_image_H.jpg</GRAND><PETIT>http://media.canal-plus.com/wwwplus/image/5/205/2/SCANDAL_SAISON_3_EXTRAITS_131107_CAN_380024_image_L.jpg</PETIT></IMAGES></MEDIA><RUBRIQUAGE><UNIVERS>SERIES</UNIVERS><RUBRIQUE>SCANDAL_SAISON_3</RUBRIQUE><CATEGORIE>EXTRAITS</CATEGORIE></RUBRIQUAGE></MEA><MEA><ID>962003</ID><TYPE>VOD STREAM</TYPE><INFOS><DESCRIPTION><![CDATA[A Washington, petits et grands secrets refont parfois surface. Le risque ? Détruire des vies, des carrières, et même des idéaux.. heureusement Olivia Pope est là ...]]></DESCRIPTION><NB_VUES>8159</NB_VUES><NB_LIKES>2</NB_LIKES><NB_COMMENTS>0</NB_COMMENTS><NOTE><AUTORISER>NON</AUTORISER><MOYENNE>0</MOYENNE><NB_VOTES>0</NB_VOTES></NOTE><TITRAGE><TITRE><![CDATA[SCANDAL]]></TITRE><SOUS_TITRE><![CDATA[Saison 3 -  Extrait de l'épisode 4 -Say Hello to my little friend]]></SOUS_TITRE></TITRAGE><OPENGRAPH><TYPE>video.other</TYPE></OPENGRAPH></INFOS><CHAINE>0</CHAINE><MEDIA><IMAGES><GRAND>http://media.canal-plus.com/wwwplus/image/5/205/2/SCANDAL_SAISON_3_EXTRAITS_131029_CAN_377462_image_H.jpg</GRAND><PETIT>http://media.canal-plus.com/wwwplus/image/5/205/2/SCANDAL_SAISON_3_EXTRAITS_131029_CAN_377462_image_L.jpg</PETIT></IMAGES></MEDIA><RUBRIQUAGE><UNIVERS>SERIES</UNIVERS><RUBRIQUE>SCANDAL_SAISON_3</RUBRIQUE><CATEGORIE>EXTRAITS</CATEGORIE></RUBRIQUAGE></MEA><MEA><ID>957879</ID><TYPE>VOD STREAM</TYPE><INFOS><DESCRIPTION><![CDATA[Olivia écartelée entre le retour de Jake, la pression de Fitz, et la prise de distance de Huck...]]></DESCRIPTION><NB_VUES>5507</NB_VUES><NB_LIKES>191</NB_LIKES><NB_COMMENTS>8</NB_COMMENTS><NOTE><AUTORISER>NON</AUTORISER><MOYENNE>0</MOYENNE><NB_VOTES>0</NB_VOTES></NOTE><TITRAGE><TITRE><![CDATA[SCANDAL]]></TITRE><SOUS_TITRE><![CDATA[Saison 3 -  Extrait de l'épisode 3 - Mrs. goes to Washington]]></SOUS_TITRE></TITRAGE><OPENGRAPH><TYPE>video.other</TYPE></OPENGRAPH></INFOS><CHAINE>0</CHAINE><MEDIA><IMAGES><GRAND>http://media.canal-plus.com/wwwplus/image/5/205/2/SCANDAL_SAISON_3_EXTRAITS_131022_CAN_375644_image_H.jpg</GRAND><PETIT>http://media.canal-plus.com/wwwplus/image/5/205/2/SCANDAL_SAISON_3_EXTRAITS_131022_CAN_375644_image_L.jpg</PETIT></IMAGES></MEDIA><RUBRIQUAGE><UNIVERS>SERIES</UNIVERS><RUBRIQUE>SCANDAL_SAISON_3</RUBRIQUE><CATEGORIE>EXTRAITS</CATEGORIE></RUBRIQUAGE></MEA><MEA><ID>954859</ID><TYPE>VOD STREAM</TYPE><INFOS><DESCRIPTION><![CDATA[Quand Olivia découvre qui est vraiment son père ...]]></DESCRIPTION><NB_VUES>9311</NB_VUES><NB_LIKES>91</NB_LIKES><NB_COMMENTS>17</NB_COMMENTS><NOTE><AUTORISER>NON</AUTORISER><MOYENNE>0</MOYENNE><NB_VOTES>0</NB_VOTES></NOTE><TITRAGE><TITRE><![CDATA[SCANDAL]]></TITRE><SOUS_TITRE><![CDATA[Saison 3 -  Extrait de l'épisode 2 - Guess who is coming to dinner]]></SOUS_TITRE></TITRAGE><OPENGRAPH><TYPE>video.other</TYPE></OPENGRAPH></INFOS><CHAINE>0</CHAINE><MEDIA><IMAGES><GRAND>http://media.canal-plus.com/wwwplus/image/5/205/2/SCANDAL_SAISON_3_EXTRAITS_131017_CAN_374297_image_H.jpg</GRAND><PETIT>http://media.canal-plus.com/wwwplus/image/5/205/2/SCANDAL_SAISON_3_EXTRAITS_131017_CAN_374297_image_L.jpg</PETIT></IMAGES></MEDIA><RUBRIQUAGE><UNIVERS>SERIES</UNIVERS><RUBRIQUE>SCANDAL_SAISON_3</RUBRIQUE><CATEGORIE>EXTRAITS</CATEGORIE></RUBRIQUAGE></MEA><MEA><ID>948897</ID><TYPE>VOD STREAM</TYPE><INFOS><DESCRIPTION><![CDATA[Cyrus met en place son plan]]></DESCRIPTION><NB_VUES>20909</NB_VUES><NB_LIKES>11</NB_LIKES><NB_COMMENTS>0</NB_COMMENTS><NOTE><AUTORISER>NON</AUTORISER><MOYENNE>0</MOYENNE><NB_VOTES>0</NB_VOTES></NOTE><TITRAGE><TITRE><![CDATA[SCANDAL]]></TITRE><SOUS_TITRE><![CDATA[Saison 3 -  Extrait de l'épisode 1 - It's handled]]></SOUS_TITRE></TITRAGE><OPENGRAPH><TYPE>video.other</TYPE></OPENGRAPH></INFOS><CHAINE>0</CHAINE><MEDIA><IMAGES><GRAND>http://media.canal-plus.com/wwwplus/image/5/205/2/VIGNETTE_AUTO_485417_H.jpg</GRAND><PETIT>http://media.canal-plus.com/wwwplus/image/5/205/2/VIGNETTE_AUTO_485416_L.jpg</PETIT></IMAGES></MEDIA><RUBRIQUAGE><UNIVERS>SERIES</UNIVERS><RUBRIQUE>SCANDAL_SAISON_3</RUBRIQUE><CATEGORIE>EXTRAITS</CATEGORIE></RUBRIQUAGE></MEA></MEAS>