<MEAS><MEA><ID>1132849</ID><TYPE>VOD STREAM</TYPE><INFOS><DESCRIPTION><![CDATA[Lucrezia se retrouve dans une position délicate avec le retour de Rodrigo Borgia. Ce dernier règne sans partage et n'hésite pas à se montrer cruel envers ses ennemis. Devenue conseillère du pape grâce à lui, Lucrezia n'arrive ni à imposer sa parole, ni à stopper les craintes de son époux, survenues avec l'arrivée de Cesare à Rome. Le fils Borgia est porté par son désir de conquête. Féroce, il est prêt à tout...]]></DESCRIPTION><NB_VUES>2595</NB_VUES><NB_LIKES>48</NB_LIKES><NB_COMMENTS>11</NB_COMMENTS><NOTE><AUTORISER>NON</AUTORISER><MOYENNE>0</MOYENNE><NB_VOTES>0</NB_VOTES></NOTE><TITRAGE><TITRE><![CDATA[BORGIA saison 3]]></TITRE><SOUS_TITRE><![CDATA[Extrait de l'épisode 2]]></SOUS_TITRE></TITRAGE><OPENGRAPH><TYPE>video.other</TYPE></OPENGRAPH></INFOS><CHAINE>0</CHAINE><MEDIA><IMAGES><GRAND>http://media.canal-plus.com/wwwplus/image/5/235/3/nip-nip-24840-640x360-yul6d.jpg</GRAND><PETIT>http://media.canal-plus.com/wwwplus/image/5/235/3/nip-nip-24840-145x109-yul6d.jpg</PETIT></IMAGES></MEDIA><RUBRIQUAGE><UNIVERS>SERIES</UNIVERS><RUBRIQUE>BORGIA_SAISON_3</RUBRIQUE><CATEGORIE>EXTRAIT</CATEGORIE></RUBRIQUAGE></MEA><MEA><ID>1132848</ID><TYPE>VOD STREAM</TYPE><INFOS><DESCRIPTION><![CDATA[Pendant que Lucrezia est à la tête du Vatican, Rodrigo Borgia continue sa retraite spirituelle. Il tente d'effacer ses sentiments amoureux pour Giulia et son désir pour sa propre fille, mariée désormais à Alfonso di Calabria. Mais même éloigné de toutes les tentations, il peine à y arriver. De son côté, sa fille, une jeune femme devenue régente, siège avec sagesse et tempérance, des qualités qui font défaut à Cesare. Celui-ci, toujours en guerre en Romagne, espère parvenir, avec un peu de chance, à défaire Catarina et tous les ennemis de la famille Borgia...]]></DESCRIPTION><NB_VUES>1136</NB_VUES><NB_LIKES>3</NB_LIKES><NB_COMMENTS>1</NB_COMMENTS><NOTE><AUTORISER>NON</AUTORISER><MOYENNE>0</MOYENNE><NB_VOTES>0</NB_VOTES></NOTE><TITRAGE><TITRE><![CDATA[BORGIA saison 3]]></TITRE><SOUS_TITRE><![CDATA[Extrait de l'épisode 1]]></SOUS_TITRE></TITRAGE><OPENGRAPH><TYPE>video.other</TYPE></OPENGRAPH></INFOS><CHAINE>0</CHAINE><MEDIA><IMAGES><GRAND>http://media.canal-plus.com/wwwplus/image/5/235/3/nip-nip-24839-640x360-vhlcz.jpg</GRAND><PETIT>http://media.canal-plus.com/wwwplus/image/5/235/3/nip-nip-24839-145x109-vhlcz.jpg</PETIT></IMAGES></MEDIA><RUBRIQUAGE><UNIVERS>SERIES</UNIVERS><RUBRIQUE>BORGIA_SAISON_3</RUBRIQUE><CATEGORIE>EXTRAIT</CATEGORIE></RUBRIQUAGE></MEA></MEAS>