<MEAS><MEA><ID>1242651</ID><TYPE>VOD STREAM</TYPE><INFOS><DESCRIPTION><![CDATA[Errol Childress un des petits-enfants illégitimes de la famille Tuttle vit une relation particulière avec sa demi-soeur...]]></DESCRIPTION><NB_VUES>477</NB_VUES><NB_LIKES>4</NB_LIKES><NB_COMMENTS>0</NB_COMMENTS><NOTE><AUTORISER>NON</AUTORISER><MOYENNE>0</MOYENNE><NB_VOTES>0</NB_VOTES></NOTE><TITRAGE><TITRE><![CDATA[True Detective]]></TITRE><SOUS_TITRE><![CDATA[Errol Childress]]></SOUS_TITRE></TITRAGE><OPENGRAPH><TYPE>video.other</TYPE></OPENGRAPH></INFOS><CHAINE>0</CHAINE><MEDIA><IMAGES><GRAND>http://media.canal-plus.com/wwwplus/image/5/277/3/VIGNETTE_AUTO_608852_H.jpg</GRAND><PETIT>http://media.canal-plus.com/wwwplus/image/5/277/3/VIGNETTE_AUTO_608851_L.jpg</PETIT></IMAGES></MEDIA><RUBRIQUAGE><UNIVERS>SERIES</UNIVERS><RUBRIQUE>TRUE_DETECTIVE_S1</RUBRIQUE><CATEGORIE>EXTRAIT</CATEGORIE></RUBRIQUAGE></MEA><MEA><ID>1242670</ID><TYPE>VOD STREAM</TYPE><INFOS><DESCRIPTION><![CDATA[Un ancien camarade de classe de Marie Fontenot raconte ce qu'il a vu alors qu'il n'était qu'un enfant...]]></DESCRIPTION><NB_VUES>139</NB_VUES><NB_LIKES>2</NB_LIKES><NB_COMMENTS>0</NB_COMMENTS><NOTE><AUTORISER>NON</AUTORISER><MOYENNE>0</MOYENNE><NB_VOTES>0</NB_VOTES></NOTE><TITRAGE><TITRE><![CDATA[True Detective]]></TITRE><SOUS_TITRE><![CDATA[Témoignage de Toby Boelert]]></SOUS_TITRE></TITRAGE><OPENGRAPH><TYPE>video.other</TYPE></OPENGRAPH></INFOS><CHAINE>0</CHAINE><MEDIA><IMAGES><GRAND>http://media.canal-plus.com/wwwplus/image/5/277/3/nip-nip-49826-640x360-vjzhc.jpg</GRAND><PETIT>http://media.canal-plus.com/wwwplus/image/5/277/3/nip-nip-49826-145x109-vjzhc.jpg</PETIT></IMAGES></MEDIA><RUBRIQUAGE><UNIVERS>SERIES</UNIVERS><RUBRIQUE>TRUE_DETECTIVE_S1</RUBRIQUE><CATEGORIE>EXTRAIT</CATEGORIE></RUBRIQUAGE></MEA><MEA><ID>1242652</ID><TYPE>VOD STREAM</TYPE><INFOS><DESCRIPTION><![CDATA[Dolores Jackson était une ancienne employée de la famille Tuttle. Elle a vu beaucoup d'enfants autour du révérend dont un qui portait des cicatrices au visage...]]></DESCRIPTION><NB_VUES>140</NB_VUES><NB_LIKES>4</NB_LIKES><NB_COMMENTS>0</NB_COMMENTS><NOTE><AUTORISER>NON</AUTORISER><MOYENNE>0</MOYENNE><NB_VOTES>0</NB_VOTES></NOTE><TITRAGE><TITRE><![CDATA[True Detective]]></TITRE><SOUS_TITRE><![CDATA[Témoignage de Dolores Jackson]]></SOUS_TITRE></TITRAGE><OPENGRAPH><TYPE>video.other</TYPE></OPENGRAPH></INFOS><CHAINE>0</CHAINE><MEDIA><IMAGES><GRAND>http://media.canal-plus.com/wwwplus/image/5/277/3/VIGNETTE_AUTO_608854_H.jpg</GRAND><PETIT>http://media.canal-plus.com/wwwplus/image/5/277/3/VIGNETTE_AUTO_608853_L.jpg</PETIT></IMAGES></MEDIA><RUBRIQUAGE><UNIVERS>SERIES</UNIVERS><RUBRIQUE>TRUE_DETECTIVE_S1</RUBRIQUE><CATEGORIE>EXTRAIT</CATEGORIE></RUBRIQUAGE></MEA><MEA><ID>1247710</ID><TYPE>VOD STREAM</TYPE><INFOS><DESCRIPTION><![CDATA[Fin de saison et fin du mystère qui tourmente les detectives Cohle et Hart (Matthew McConaughey et Woody Harrelson)]]></DESCRIPTION><NB_VUES>771</NB_VUES><NB_LIKES>5</NB_LIKES><NB_COMMENTS>1</NB_COMMENTS><NOTE><AUTORISER>NON</AUTORISER><MOYENNE>0</MOYENNE><NB_VOTES>0</NB_VOTES></NOTE><TITRAGE><TITRE><![CDATA[True Detective]]></TITRE><SOUS_TITRE><![CDATA[Episodes 7 et 8 le 14 mai sur CANAL+]]></SOUS_TITRE></TITRAGE><OPENGRAPH><TYPE>video.other</TYPE></OPENGRAPH></INFOS><CHAINE>0</CHAINE><MEDIA><IMAGES><GRAND>http://media.canal-plus.com/wwwplus/image/5/277/1/nip-nip-50942-640x360-nva0u.jpg</GRAND><PETIT>http://media.canal-plus.com/wwwplus/image/5/277/1/nip-nip-50942-145x109-nva0u.jpg</PETIT></IMAGES></MEDIA><RUBRIQUAGE><UNIVERS>SERIES</UNIVERS><RUBRIQUE>TRUE_DETECTIVE_S1</RUBRIQUE><CATEGORIE>BA</CATEGORIE></RUBRIQUAGE></MEA><MEA><ID>1242659</ID><TYPE>VOD STREAM</TYPE><INFOS><DESCRIPTION><![CDATA[Kelly Reider la fillette retrouvée en état catatonique en 1995 dans la cabane de Reggie Ledoux, témoigne de ses bourreaux 7 ans après...]]></DESCRIPTION><NB_VUES>303</NB_VUES><NB_LIKES>0</NB_LIKES><NB_COMMENTS>0</NB_COMMENTS><NOTE><AUTORISER>NON</AUTORISER><MOYENNE>0</MOYENNE><NB_VOTES>0</NB_VOTES></NOTE><TITRAGE><TITRE><![CDATA[True Detective]]></TITRE><SOUS_TITRE><![CDATA[Son visage...]]></SOUS_TITRE></TITRAGE><OPENGRAPH><TYPE>video.other</TYPE></OPENGRAPH></INFOS><CHAINE>0</CHAINE><MEDIA><IMAGES><GRAND>http://media.canal-plus.com/wwwplus/image/5/277/3/VIGNETTE_AUTO_608856_H.jpg</GRAND><PETIT>http://media.canal-plus.com/wwwplus/image/5/277/3/VIGNETTE_AUTO_608855_L.jpg</PETIT></IMAGES></MEDIA><RUBRIQUAGE><UNIVERS>SERIES</UNIVERS><RUBRIQUE>TRUE_DETECTIVE_S1</RUBRIQUE><CATEGORIE>EXTRAIT</CATEGORIE></RUBRIQUAGE></MEA><MEA><ID>1242636</ID><TYPE>VOD STREAM</TYPE><INFOS><DESCRIPTION><![CDATA[L'ancien révérend raconte à Rust Cohle (Matthew McConaughey) ce qu'il a vu au cours de son séminaire à l'église de Bâton rouge du révérend Tuttle.]]></DESCRIPTION><NB_VUES>225</NB_VUES><NB_LIKES>4</NB_LIKES><NB_COMMENTS>0</NB_COMMENTS><NOTE><AUTORISER>NON</AUTORISER><MOYENNE>0</MOYENNE><NB_VOTES>0</NB_VOTES></NOTE><TITRAGE><TITRE><![CDATA[True Detective]]></TITRE><SOUS_TITRE><![CDATA[Témoignage de Justin Theriot]]></SOUS_TITRE></TITRAGE><OPENGRAPH><TYPE>video.other</TYPE></OPENGRAPH></INFOS><CHAINE>0</CHAINE><MEDIA><IMAGES><GRAND>http://media.canal-plus.com/wwwplus/image/5/277/3/VIGNETTE_AUTO_608848_H.jpg</GRAND><PETIT>http://media.canal-plus.com/wwwplus/image/5/277/3/VIGNETTE_AUTO_608847_L.jpg</PETIT></IMAGES></MEDIA><RUBRIQUAGE><UNIVERS>SERIES</UNIVERS><RUBRIQUE>TRUE_DETECTIVE_S1</RUBRIQUE><CATEGORIE>EXTRAIT</CATEGORIE></RUBRIQUAGE></MEA><MEA><ID>1242655</ID><TYPE>VOD STREAM</TYPE><INFOS><DESCRIPTION><![CDATA[Alors qu'il interroge Guy Françis, un junkie accusé de double-meurtre, Rust Cohle (Matthew McConaughey) entend parler à nouveau du Roi Jaune...]]></DESCRIPTION><NB_VUES>223</NB_VUES><NB_LIKES>4</NB_LIKES><NB_COMMENTS>0</NB_COMMENTS><NOTE><AUTORISER>NON</AUTORISER><MOYENNE>0</MOYENNE><NB_VOTES>0</NB_VOTES></NOTE><TITRAGE><TITRE><![CDATA[True Detective]]></TITRE><SOUS_TITRE><![CDATA[Le roi Jaune tue toujours]]></SOUS_TITRE></TITRAGE><OPENGRAPH><TYPE>video.other</TYPE></OPENGRAPH></INFOS><CHAINE>0</CHAINE><MEDIA><IMAGES><GRAND>http://media.canal-plus.com/wwwplus/image/5/277/3/nip-nip-49820-640x360-sezjz.jpg</GRAND><PETIT>http://media.canal-plus.com/wwwplus/image/5/277/3/nip-nip-49820-145x109-sezjz.jpg</PETIT></IMAGES></MEDIA><RUBRIQUAGE><UNIVERS>SERIES</UNIVERS><RUBRIQUE>TRUE_DETECTIVE_S1</RUBRIQUE><CATEGORIE>EXTRAIT</CATEGORIE></RUBRIQUAGE></MEA><MEA><ID>1260415</ID><TYPE>VOD STREAM</TYPE><INFOS><DESCRIPTION><![CDATA[Le meilleur du Grand Journal !]]></DESCRIPTION><NB_VUES>11395</NB_VUES><NB_LIKES>1637</NB_LIKES><NB_COMMENTS>231</NB_COMMENTS><NOTE><AUTORISER>OUI</AUTORISER><MOYENNE>0</MOYENNE><NB_VOTES>0</NB_VOTES></NOTE><TITRAGE><TITRE><![CDATA[Vrais detectives]]></TITRE><SOUS_TITRE><![CDATA[Le Grand Journal du 07/05]]></SOUS_TITRE></TITRAGE><OPENGRAPH><TYPE>video.other</TYPE></OPENGRAPH></INFOS><CHAINE>0</CHAINE><MEDIA><IMAGES><GRAND>http://media.canal-plus.com/wwwplus/image/6/15/29/nip-nip-53808-640x360-werqs.jpg</GRAND><PETIT>http://media.canal-plus.com/wwwplus/image/6/15/29/nip-nip-53808-145x109-werqs.jpg</PETIT></IMAGES></MEDIA><RUBRIQUAGE><UNIVERS>DOCUS_INFOS</UNIVERS><RUBRIQUE>LE_GRAND_JOURNAL</RUBRIQUE><CATEGORIE>EXTRAIT</CATEGORIE></RUBRIQUAGE></MEA><MEA><ID>1248891</ID><TYPE>VOD STREAM</TYPE><INFOS><DESCRIPTION><![CDATA[Suite de l'enquête des detectives Rust Cohle et Martin Hart sur CANAL+]]></DESCRIPTION><NB_VUES>1135</NB_VUES><NB_LIKES>1</NB_LIKES><NB_COMMENTS>0</NB_COMMENTS><NOTE><AUTORISER>NON</AUTORISER><MOYENNE>0</MOYENNE><NB_VOTES>0</NB_VOTES></NOTE><TITRAGE><TITRE><![CDATA[True Detective]]></TITRE><SOUS_TITRE><![CDATA[Episodes 5 et 6 le 7 mai sur CANAL+]]></SOUS_TITRE></TITRAGE><OPENGRAPH><TYPE>video.other</TYPE></OPENGRAPH></INFOS><CHAINE>0</CHAINE><MEDIA><IMAGES><GRAND>http://media.canal-plus.com/wwwplus/image/5/277/1/nip-nip-51246-640x360-ofu3m.jpg</GRAND><PETIT>http://media.canal-plus.com/wwwplus/image/5/277/1/nip-nip-51246-145x109-ofu3m.jpg</PETIT></IMAGES></MEDIA><RUBRIQUAGE><UNIVERS>SERIES</UNIVERS><RUBRIQUE>TRUE_DETECTIVE_S1</RUBRIQUE><CATEGORIE>BA</CATEGORIE></RUBRIQUAGE></MEA><MEA><ID>1242665</ID><TYPE>VOD STREAM</TYPE><INFOS><DESCRIPTION><![CDATA[Alors qu'elle avait été retrouvée noyée en 1993, Rianne Olivier portait les mêmes marques que Dora Lange sur son corps...]]></DESCRIPTION><NB_VUES>417</NB_VUES><NB_LIKES>3</NB_LIKES><NB_COMMENTS>0</NB_COMMENTS><NOTE><AUTORISER>NON</AUTORISER><MOYENNE>0</MOYENNE><NB_VOTES>0</NB_VOTES></NOTE><TITRAGE><TITRE><![CDATA[True Detective]]></TITRE><SOUS_TITRE><![CDATA[Le corps de Rianne Olivier porte d'étranges marques]]></SOUS_TITRE></TITRAGE><OPENGRAPH><TYPE>video.other</TYPE></OPENGRAPH></INFOS><CHAINE>0</CHAINE><MEDIA><IMAGES><GRAND>http://media.canal-plus.com/wwwplus/image/5/277/3/VIGNETTE_AUTO_608866_H.jpg</GRAND><PETIT>http://media.canal-plus.com/wwwplus/image/5/277/3/VIGNETTE_AUTO_608865_L.jpg</PETIT></IMAGES></MEDIA><RUBRIQUAGE><UNIVERS>SERIES</UNIVERS><RUBRIQUE>TRUE_DETECTIVE_S1</RUBRIQUE><CATEGORIE>EXTRAIT</CATEGORIE></RUBRIQUAGE></MEA><MEA><ID>1242649</ID><TYPE>VOD STREAM</TYPE><INFOS><DESCRIPTION><![CDATA[En prison, Charlie Lange raconte comment il a rencontré Reggie Ledoux...]]></DESCRIPTION><NB_VUES>371</NB_VUES><NB_LIKES>4</NB_LIKES><NB_COMMENTS>0</NB_COMMENTS><NOTE><AUTORISER>NON</AUTORISER><MOYENNE>0</MOYENNE><NB_VOTES>0</NB_VOTES></NOTE><TITRAGE><TITRE><![CDATA[True Detective]]></TITRE><SOUS_TITRE><![CDATA[Charlie Lange parle de Reggie Ledoux]]></SOUS_TITRE></TITRAGE><OPENGRAPH><TYPE>video.other</TYPE></OPENGRAPH></INFOS><CHAINE>0</CHAINE><MEDIA><IMAGES><GRAND>http://media.canal-plus.com/wwwplus/image/5/277/3/VIGNETTE_AUTO_608850_H.jpg</GRAND><PETIT>http://media.canal-plus.com/wwwplus/image/5/277/3/VIGNETTE_AUTO_608849_L.jpg</PETIT></IMAGES></MEDIA><RUBRIQUAGE><UNIVERS>SERIES</UNIVERS><RUBRIQUE>TRUE_DETECTIVE_S1</RUBRIQUE><CATEGORIE>EXTRAIT</CATEGORIE></RUBRIQUAGE></MEA><MEA><ID>1237871</ID><TYPE>VOD STREAM</TYPE><INFOS><DESCRIPTION><![CDATA[Bande annonce des épisodes 3 et 4 de la saison 1 de True Detective diffusée chaque jeudi sur CANAL+]]></DESCRIPTION><NB_VUES>746</NB_VUES><NB_LIKES>2</NB_LIKES><NB_COMMENTS>0</NB_COMMENTS><NOTE><AUTORISER>NON</AUTORISER><MOYENNE>0</MOYENNE><NB_VOTES>0</NB_VOTES></NOTE><TITRAGE><TITRE><![CDATA[True Detective]]></TITRE><SOUS_TITRE><![CDATA[Episodes 3 et 4 le 30 avril sur CANAL+]]></SOUS_TITRE></TITRAGE><OPENGRAPH><TYPE>video.other</TYPE></OPENGRAPH></INFOS><CHAINE>0</CHAINE><MEDIA><IMAGES><GRAND>http://media.canal-plus.com/wwwplus/image/5/277/1/nip-nip-48677-640x360-vtq1y.jpg</GRAND><PETIT>http://media.canal-plus.com/wwwplus/image/5/277/1/nip-nip-48677-145x109-vtq1y.jpg</PETIT></IMAGES></MEDIA><RUBRIQUAGE><UNIVERS>SERIES</UNIVERS><RUBRIQUE>TRUE_DETECTIVE_S1</RUBRIQUE><CATEGORIE>BA</CATEGORIE></RUBRIQUAGE></MEA><MEA><ID>1242664</ID><TYPE>VOD STREAM</TYPE><INFOS><DESCRIPTION><![CDATA[C'est aux environs d'Erath que Rust Cohle (Matthew McConaughey) et Martin Hart (Woody Harrelson) découvre la macabre mise en scène du meurtre de Dora Lange, le 3 janvier 1995.]]></DESCRIPTION><NB_VUES>825</NB_VUES><NB_LIKES>5</NB_LIKES><NB_COMMENTS>4</NB_COMMENTS><NOTE><AUTORISER>NON</AUTORISER><MOYENNE>0</MOYENNE><NB_VOTES>0</NB_VOTES></NOTE><TITRAGE><TITRE><![CDATA[True Detective]]></TITRE><SOUS_TITRE><![CDATA[Découverte du corps de Dora Lange]]></SOUS_TITRE></TITRAGE><OPENGRAPH><TYPE>video.other</TYPE></OPENGRAPH></INFOS><CHAINE>0</CHAINE><MEDIA><IMAGES><GRAND>http://media.canal-plus.com/wwwplus/image/5/277/3/VIGNETTE_AUTO_608864_H.jpg</GRAND><PETIT>http://media.canal-plus.com/wwwplus/image/5/277/3/VIGNETTE_AUTO_608863_L.jpg</PETIT></IMAGES></MEDIA><RUBRIQUAGE><UNIVERS>SERIES</UNIVERS><RUBRIQUE>TRUE_DETECTIVE_S1</RUBRIQUE><CATEGORIE>EXTRAIT</CATEGORIE></RUBRIQUAGE></MEA><MEA><ID>1242663</ID><TYPE>VOD STREAM</TYPE><INFOS><DESCRIPTION><![CDATA[Ces drôles de structures en brindilles se trouvent partout sur la piste du meurtrier, mais que sont-elles vraiment ?]]></DESCRIPTION><NB_VUES>376</NB_VUES><NB_LIKES>0</NB_LIKES><NB_COMMENTS>0</NB_COMMENTS><NOTE><AUTORISER>NON</AUTORISER><MOYENNE>0</MOYENNE><NB_VOTES>0</NB_VOTES></NOTE><TITRAGE><TITRE><![CDATA[True Detective]]></TITRE><SOUS_TITRE><![CDATA[Les pièges à oiseaux]]></SOUS_TITRE></TITRAGE><OPENGRAPH><TYPE>video.other</TYPE></OPENGRAPH></INFOS><CHAINE>0</CHAINE><MEDIA><IMAGES><GRAND>http://media.canal-plus.com/wwwplus/image/5/277/3/VIGNETTE_AUTO_608862_H.jpg</GRAND><PETIT>http://media.canal-plus.com/wwwplus/image/5/277/3/VIGNETTE_AUTO_608861_L.jpg</PETIT></IMAGES></MEDIA><RUBRIQUAGE><UNIVERS>SERIES</UNIVERS><RUBRIQUE>TRUE_DETECTIVE_S1</RUBRIQUE><CATEGORIE>EXTRAIT</CATEGORIE></RUBRIQUAGE></MEA><MEA><ID>1249872</ID><TYPE>VOD STREAM</TYPE><INFOS><DESCRIPTION><![CDATA[Les acteurs de la série dévoilent leurs vision de l'enquête et les coulisses de la série.]]></DESCRIPTION><NB_VUES>1003</NB_VUES><NB_LIKES>170</NB_LIKES><NB_COMMENTS>13</NB_COMMENTS><NOTE><AUTORISER>NON</AUTORISER><MOYENNE>0</MOYENNE><NB_VOTES>0</NB_VOTES></NOTE><TITRAGE><TITRE><![CDATA[True Detective]]></TITRE><SOUS_TITRE><![CDATA[L'interview des acteurs]]></SOUS_TITRE></TITRAGE><OPENGRAPH><TYPE>video.other</TYPE></OPENGRAPH></INFOS><CHAINE>0</CHAINE><MEDIA><IMAGES><GRAND>http://media.canal-plus.com/wwwplus/image/5/277/2/VIGNETTE_AUTO_612060_H.jpg</GRAND><PETIT>http://media.canal-plus.com/wwwplus/image/5/277/2/VIGNETTE_AUTO_612059_L.jpg</PETIT></IMAGES></MEDIA><RUBRIQUAGE><UNIVERS>SERIES</UNIVERS><RUBRIQUE>TRUE_DETECTIVE_S1</RUBRIQUE><CATEGORIE>BONUS</CATEGORIE></RUBRIQUAGE></MEA><MEA><ID>1242660</ID><TYPE>VOD STREAM</TYPE><INFOS><DESCRIPTION><![CDATA[2012, Martin Hart (Woody Harrelson) est interrogé par 2 policiers concernant une affaire sur laquelle il a enquêté en 1995.]]></DESCRIPTION><NB_VUES>827</NB_VUES><NB_LIKES>5</NB_LIKES><NB_COMMENTS>0</NB_COMMENTS><NOTE><AUTORISER>NON</AUTORISER><MOYENNE>0</MOYENNE><NB_VOTES>0</NB_VOTES></NOTE><TITRAGE><TITRE><![CDATA[True Detective]]></TITRE><SOUS_TITRE><![CDATA[L'interrogatoire]]></SOUS_TITRE></TITRAGE><OPENGRAPH><TYPE>video.other</TYPE></OPENGRAPH></INFOS><CHAINE>0</CHAINE><MEDIA><IMAGES><GRAND>http://media.canal-plus.com/wwwplus/image/5/277/3/VIGNETTE_AUTO_608858_H.jpg</GRAND><PETIT>http://media.canal-plus.com/wwwplus/image/5/277/3/VIGNETTE_AUTO_608857_L.jpg</PETIT></IMAGES></MEDIA><RUBRIQUAGE><UNIVERS>SERIES</UNIVERS><RUBRIQUE>TRUE_DETECTIVE_S1</RUBRIQUE><CATEGORIE>EXTRAIT</CATEGORIE></RUBRIQUAGE></MEA><MEA><ID>1235072</ID><TYPE>VOD STREAM</TYPE><INFOS><DESCRIPTION><![CDATA[Woody Harrelson et Matthew McConaughey enquêtent sur une sordide affaire de meurtre au coeur de la Louisiane...
Bientôt sur CANAL+,  4 soirées pour percer un mystère de plus de 30 ans]]></DESCRIPTION><NB_VUES>923</NB_VUES><NB_LIKES>0</NB_LIKES><NB_COMMENTS>0</NB_COMMENTS><NOTE><AUTORISER>NON</AUTORISER><MOYENNE>0</MOYENNE><NB_VOTES>0</NB_VOTES></NOTE><TITRAGE><TITRE><![CDATA[True Detective]]></TITRE><SOUS_TITRE><![CDATA[Un mystère infini...]]></SOUS_TITRE></TITRAGE><OPENGRAPH><TYPE>video.other</TYPE></OPENGRAPH></INFOS><CHAINE>0</CHAINE><MEDIA><IMAGES><GRAND>http://media.canal-plus.com/wwwplus/image/5/277/1/VIGNETTE_AUTO_605338_H.jpg</GRAND><PETIT>http://media.canal-plus.com/wwwplus/image/5/277/1/VIGNETTE_AUTO_605337_L.jpg</PETIT></IMAGES></MEDIA><RUBRIQUAGE><UNIVERS>SERIES</UNIVERS><RUBRIQUE>TRUE_DETECTIVE_S1</RUBRIQUE><CATEGORIE>BA</CATEGORIE></RUBRIQUAGE></MEA><MEA><ID>1236249</ID><TYPE>VOD STREAM</TYPE><INFOS><DESCRIPTION><![CDATA[Matthew Mc Conaughey et Woody Harrelson pour résoudre une enquête mystérieuse... Dès le 23 avril sur CANAL+]]></DESCRIPTION><NB_VUES>1784</NB_VUES><NB_LIKES>38</NB_LIKES><NB_COMMENTS>14</NB_COMMENTS><NOTE><AUTORISER>NON</AUTORISER><MOYENNE>0</MOYENNE><NB_VOTES>0</NB_VOTES></NOTE><TITRAGE><TITRE><![CDATA[True Detective]]></TITRE><SOUS_TITRE><![CDATA[Le phénomène arrive sur CANAL+]]></SOUS_TITRE></TITRAGE><OPENGRAPH><TYPE>video.other</TYPE></OPENGRAPH></INFOS><CHAINE>0</CHAINE><MEDIA><IMAGES><GRAND>http://media.canal-plus.com/wwwplus/image/5/277/1/VIGNETTE_AUTO_605407_H.jpg</GRAND><PETIT>http://media.canal-plus.com/wwwplus/image/5/277/1/VIGNETTE_AUTO_605406_L.jpg</PETIT></IMAGES></MEDIA><RUBRIQUAGE><UNIVERS>SERIES</UNIVERS><RUBRIQUE>TRUE_DETECTIVE_S1</RUBRIQUE><CATEGORIE>BA</CATEGORIE></RUBRIQUAGE></MEA><MEA><ID>1240628</ID><TYPE>VOD STREAM</TYPE><INFOS><DESCRIPTION><![CDATA[A partir du 23 avril sur CANAL+]]></DESCRIPTION><NB_VUES>98326</NB_VUES><NB_LIKES>69</NB_LIKES><NB_COMMENTS>24</NB_COMMENTS><NOTE><AUTORISER>NON</AUTORISER><MOYENNE>0</MOYENNE><NB_VOTES>0</NB_VOTES></NOTE><TITRAGE><TITRE><![CDATA[True Detective]]></TITRE><SOUS_TITRE><![CDATA[4 soirées pour résoudre un mystère]]></SOUS_TITRE></TITRAGE><OPENGRAPH><TYPE>video.other</TYPE></OPENGRAPH></INFOS><CHAINE>0</CHAINE><MEDIA><IMAGES><GRAND>http://media.canal-plus.com/wwwplus/image/5/277/1/VIGNETTE_AUTO_607465_H.jpg</GRAND><PETIT>http://media.canal-plus.com/wwwplus/image/5/277/1/VIGNETTE_AUTO_607464_L.jpg</PETIT></IMAGES></MEDIA><RUBRIQUAGE><UNIVERS>SERIES</UNIVERS><RUBRIQUE>TRUE_DETECTIVE_S1</RUBRIQUE><CATEGORIE>BA</CATEGORIE></RUBRIQUAGE></MEA><MEA><ID>1236248</ID><TYPE>VOD STREAM</TYPE><INFOS><DESCRIPTION><![CDATA[La série culte arrive sur CANAL+ avec Matthew Mc Connaughey et Woody Harrelson]]></DESCRIPTION><NB_VUES>2848</NB_VUES><NB_LIKES>52</NB_LIKES><NB_COMMENTS>26</NB_COMMENTS><NOTE><AUTORISER>NON</AUTORISER><MOYENNE>0</MOYENNE><NB_VOTES>0</NB_VOTES></NOTE><TITRAGE><TITRE><![CDATA[True Detective]]></TITRE><SOUS_TITRE><![CDATA[A partir du 23 avril]]></SOUS_TITRE></TITRAGE><OPENGRAPH><TYPE>video.other</TYPE></OPENGRAPH></INFOS><CHAINE>0</CHAINE><MEDIA><IMAGES><GRAND>http://media.canal-plus.com/wwwplus/image/5/277/1/VIGNETTE_AUTO_605405_H.jpg</GRAND><PETIT>http://media.canal-plus.com/wwwplus/image/5/277/1/VIGNETTE_AUTO_605404_L.jpg</PETIT></IMAGES></MEDIA><RUBRIQUAGE><UNIVERS>SERIES</UNIVERS><RUBRIQUE>TRUE_DETECTIVE_S1</RUBRIQUE><CATEGORIE>BA</CATEGORIE></RUBRIQUAGE></MEA></MEAS>