<MEAS><MEA><ID>1269829</ID><TYPE>VOD STREAM</TYPE><INFOS><DESCRIPTION><![CDATA[Aujourd'hui, on tire sur une ambulance !]]></DESCRIPTION><NB_VUES>147159</NB_VUES><NB_LIKES>460</NB_LIKES><NB_COMMENTS>96</NB_COMMENTS><NOTE><AUTORISER>NON</AUTORISER><MOYENNE>5</MOYENNE><NB_VOTES>1</NB_VOTES></NOTE><TITRAGE><TITRE><![CDATA[Entre Panthéon et Eurovision]]></TITRE><SOUS_TITRE><![CDATA[Le Petit Journal du 28/05]]></SOUS_TITRE></TITRAGE><OPENGRAPH><TYPE>video.other</TYPE></OPENGRAPH></INFOS><CHAINE>0</CHAINE><MEDIA><IMAGES><GRAND>http://media.canal-plus.com/wwwplus/image/4/12/3/VIGNETTE_AUTO_624524_H.jpg</GRAND><PETIT>http://media.canal-plus.com/wwwplus/image/4/12/3/VIGNETTE_AUTO_624523_L.jpg</PETIT></IMAGES></MEDIA><RUBRIQUAGE><UNIVERS>DIVERTISSEMENT</UNIVERS><RUBRIQUE>LE_PETIT_JOURNAL</RUBRIQUE><CATEGORIE>QUOTIDIEN</CATEGORIE></RUBRIQUAGE></MEA><MEA><ID>1269340</ID><TYPE>VOD STREAM</TYPE><INFOS><DESCRIPTION><![CDATA[Yann Barthès présente LE PETIT JOURNAL, un regard décalé sur l'actualité.]]></DESCRIPTION><NB_VUES>121514</NB_VUES><NB_LIKES>229</NB_LIKES><NB_COMMENTS>37</NB_COMMENTS><NOTE><AUTORISER>OUI</AUTORISER><MOYENNE>0</MOYENNE><NB_VOTES>0</NB_VOTES></NOTE><TITRAGE><TITRE><![CDATA[Avec Shamir]]></TITRE><SOUS_TITRE><![CDATA[Le Petit Journal du 27/05]]></SOUS_TITRE></TITRAGE><OPENGRAPH><TYPE>video.other</TYPE></OPENGRAPH></INFOS><CHAINE>0</CHAINE><MEDIA><IMAGES><GRAND>http://media.canal-plus.com/wwwplus/image/4/12/3/nip-nip-56161-640x360-v3fge.jpg</GRAND><PETIT>http://media.canal-plus.com/wwwplus/image/4/12/3/nip-nip-56161-145x109-v3fge.jpg</PETIT></IMAGES></MEDIA><RUBRIQUAGE><UNIVERS>DIVERTISSEMENT</UNIVERS><RUBRIQUE>LE_PETIT_JOURNAL</RUBRIQUE><CATEGORIE>QUOTIDIEN</CATEGORIE></RUBRIQUAGE></MEA><MEA><ID>1258808</ID><TYPE>VOD STREAM</TYPE><INFOS><DESCRIPTION><![CDATA[Le meilleur du Petit Journal de Yann Barthès !]]></DESCRIPTION><NB_VUES>1099041</NB_VUES><NB_LIKES>82839</NB_LIKES><NB_COMMENTS>17653</NB_COMMENTS><NOTE><AUTORISER>NON</AUTORISER><MOYENNE>0</MOYENNE><NB_VOTES>0</NB_VOTES></NOTE><TITRAGE><TITRE><![CDATA[Agression de nos journalistes : ce qu'il s'est passé]]></TITRE><SOUS_TITRE><![CDATA[Le Petit Journal du 04/05]]></SOUS_TITRE></TITRAGE><OPENGRAPH><TYPE>video.other</TYPE></OPENGRAPH></INFOS><CHAINE>0</CHAINE><MEDIA><IMAGES><GRAND>http://media.canal-plus.com/wwwplus/image/4/12/1/nip-nip-53420-640x360-udv2r.jpg</GRAND><PETIT>http://media.canal-plus.com/wwwplus/image/4/12/1/nip-nip-53420-145x109-udv2r.jpg</PETIT></IMAGES></MEDIA><RUBRIQUAGE><UNIVERS>DIVERTISSEMENT</UNIVERS><RUBRIQUE>LE_PETIT_JOURNAL</RUBRIQUE><CATEGORIE>BONUS</CATEGORIE></RUBRIQUAGE></MEA><MEA><ID>1270795</ID><TYPE>VOD STREAM</TYPE><INFOS><DESCRIPTION><![CDATA[Le meilleur de toutes les chaînes, tous les jours]]></DESCRIPTION><NB_VUES>8831</NB_VUES><NB_LIKES>0</NB_LIKES><NB_COMMENTS>0</NB_COMMENTS><NOTE><AUTORISER>NON</AUTORISER><MOYENNE>0</MOYENNE><NB_VOTES>0</NB_VOTES></NOTE><TITRAGE><TITRE><![CDATA[Le Zapping de la semaine]]></TITRE><SOUS_TITRE><![CDATA[31/05/15]]></SOUS_TITRE></TITRAGE><OPENGRAPH><TYPE>video.other</TYPE></OPENGRAPH></INFOS><CHAINE>0</CHAINE><MEDIA><IMAGES><GRAND>http://media.canal-plus.com/wwwplus/image/6/20/1/VIGNETTE_AUTO_624889_H.jpg</GRAND><PETIT>http://media.canal-plus.com/wwwplus/image/6/20/1/VIGNETTE_AUTO_624888_L.jpg</PETIT></IMAGES></MEDIA><RUBRIQUAGE><UNIVERS>DOCUS_INFOS</UNIVERS><RUBRIQUE>ZAPPING</RUBRIQUE><CATEGORIE>EMISSION</CATEGORIE></RUBRIQUAGE></MEA><MEA><ID>1270577</ID><TYPE>VOD STREAM</TYPE><INFOS><DESCRIPTION><![CDATA[Le meilleur de toutes les chaînes, tous les jours]]></DESCRIPTION><NB_VUES>24130</NB_VUES><NB_LIKES>0</NB_LIKES><NB_COMMENTS>0</NB_COMMENTS><NOTE><AUTORISER>NON</AUTORISER><MOYENNE>0</MOYENNE><NB_VOTES>0</NB_VOTES></NOTE><TITRAGE><TITRE><![CDATA[Le Zapping]]></TITRE><SOUS_TITRE><![CDATA[30/05/15]]></SOUS_TITRE></TITRAGE><OPENGRAPH><TYPE>video.other</TYPE></OPENGRAPH></INFOS><CHAINE>0</CHAINE><MEDIA><IMAGES><GRAND>http://media.canal-plus.com/wwwplus/image/6/20/1/VIGNETTE_AUTO_624826_H.jpg</GRAND><PETIT>http://media.canal-plus.com/wwwplus/image/6/20/1/VIGNETTE_AUTO_624825_L.jpg</PETIT></IMAGES></MEDIA><RUBRIQUAGE><UNIVERS>DOCUS_INFOS</UNIVERS><RUBRIQUE>ZAPPING</RUBRIQUE><CATEGORIE>EMISSION</CATEGORIE></RUBRIQUAGE></MEA></MEAS>